pysats/__init__.py
pysats/generic_model.py
pysats/gsvm.py
pysats/lsvm.py
pysats/mrvm.py
pysats/pysats.py
pysats/simple_model.py
pysats/srvm.py
pysats-0.2.2.dist-info/LICENSE
pysats-0.2.2.dist-info/METADATA
pysats-0.2.2.dist-info/WHEEL
pysats-0.2.2.dist-info/RECORD
