Metadata-Version: 2.1
Name: pysats
Version: 0.2.2
Summary: GNU Affero General Public License v3
Home-page: https://github.com/marketdesignresearch/pysats
License: GNU Affero General Public License v3
Author: Fabio Isler
Author-email: islerfab@gmail.com
Requires-Python: >=3.8,<4.0
Classifier: License :: Other/Proprietary License
Classifier: Programming Language :: Python :: 3
Classifier: Programming Language :: Python :: 3.8
Classifier: Programming Language :: Python :: 3.9
Classifier: Programming Language :: Python :: 3.10
Classifier: Programming Language :: Python :: 3.11
Requires-Dist: Cython (>=0.29.23,<0.30.0)
Requires-Dist: numpy (>=1.24.1,<2.0.0)
Requires-Dist: pyjnius (>=1.3.0,<2.0.0)
Project-URL: Repository, https://github.com/marketdesignresearch/pysats
